Workbook

Sheet 発注書フォーマット
A1: ORDER SHEET
H3: 注文日 | I3: 46127
A4: 発注先
A5: 株式会社アスプルンド 御中
A8: 下記の通り発注いたしますので、ご手配の程お願い致します。
A10: 出荷日
A12: 納品予定日
A14: 処理番号
A17: ご納品先 | C17: 都道府県 | D17: 東京都 | G17: お届け日目安 | H17: =IFERROR(VLOOKUP(D17,'送料対応表'!A:C,3,0),"") -> 1日～2日
E18: 合計 | G18: =IFERROR(I30,"") -> 84000
A20: 品番 | C20: 商品名 | G20: カラー | H20: 数量 | I20: 単価 | J20: 小計
A21: 293660 | C21: HOUGAN DESK TOP Charcoal | G21: =IFERROR(VLOOKUP(A21,'リスト'!A:T,5,0),"") | H21: 2 | I21: =IFERROR(VLOOKUP(A21,'リスト'!A:T,8,0),"") -> 28000 | J21: =IFERROR(H21*I21,"") -> 56000
A22: 293677 | C22: HOUGAN DESK END LEG Black(4pcs/1set) | G22: =IFERROR(VLOOKUP(A22,'リスト'!A:T,5,0),"") | H22: 2 | I22: =IFERROR(VLOOKUP(A22,'リスト'!A:T,8,0),"") -> 14000 | J22: =IFERROR(H22*I22,"") -> 28000
C23: =IFERROR(VLOOKUP(A23,'リスト'!A:T,3,0),"") | G23: =IFERROR(VLOOKUP(A23,'リスト'!A:T,5,0),"") | I23: =IFERROR(VLOOKUP(A23,'リスト'!A:T,8,0),"") | J23: =IFERROR(H23*I23,"") -> 0
C24: =IFERROR(VLOOKUP(A24,'リスト'!A:T,3,0),"") | G24: =IFERROR(VLOOKUP(A24,'リスト'!A:T,5,0),"") | I24: =IFERROR(VLOOKUP(A24,'リスト'!A:T,8,0),"") | J24: =IFERROR(H24*I24,"") -> 0
C25: =IFERROR(VLOOKUP(A25,'リスト'!A:T,3,0),"") | G25: =IFERROR(VLOOKUP(A25,'リスト'!A:T,5,0),"") | I25: =IFERROR(VLOOKUP(A25,'リスト'!A:T,8,0),"") | J25: =IFERROR(H25*I25,"") -> 0
C26: =IFERROR(VLOOKUP(A26,'リスト'!A:T,3,0),"") | G26: =IFERROR(VLOOKUP(A26,'リスト'!A:T,5,0),"") | I26: =IFERROR(VLOOKUP(A26,'リスト'!A:T,8,0),"") | J26: =IFERROR(H26*I26,"") -> 0
C27: =IFERROR(VLOOKUP(A27,'リスト'!A:T,3,0),"") | G27: =IFERROR(VLOOKUP(A27,'リスト'!A:T,5,0),"") | I27: =IFERROR(VLOOKUP(A27,'リスト'!A:T,8,0),"") | J27: =IFERROR(H27*I27,"") -> 0
C28: =IFERROR(VLOOKUP(A28,'リスト'!A:T,3,0),"") | G28: =IFERROR(VLOOKUP(A28,'リスト'!A:T,5,0),"") | I28: =IFERROR(VLOOKUP(A28,'リスト'!A:T,8,0),"") | J28: =IFERROR(H28*I28,"") -> 0
A29: 送料 | I29: =IFERROR(VLOOKUP(D17,'送料対応表'!A:B,2,0),"") -> 0
A30: 計 | I30: =IFERROR(SUM(J21:J28)+I29,"") -> 84000
A31: 消費税等 (10%) | I31: =IFERROR(I30*0.1,"") -> 8400
A32: 御請求額 | I32: =IFERROR(I30*1.1,"") -> 92400
A34: 納品先
A35: ご住所 | C35: 〒160-0008 東京都新宿区四谷三栄町9-6四谷三栄町スクエア4階
A36: お電話番号 | C36: 0362731031
A37: 受取人様名 | C37: 野坂桃子 KH株式会社
A39: お取引条件 | C39: お支払方法 | G39: 備考
A40: 従来通り | C40: 末日締め/翌末日払い | G40: 弊社注文番号：#9004 2026-04-20 午後着でお願いいたします。

Sheet リスト
A1: 品番 | B1: 画像 | C1: 商品名 | D1: 商品名フリガナ | E1: カラー | F1: 上代(税抜) | G1: 上代(税込) | H1: 下代 | I1: 商品サイズ | J1: 素材詳細 | K1: 生産国 | L1: N.W. （㎏） | M1: 外装 W (㎜) | N1: 外装 D （㎜） | O1: 外装 H （㎜） | P1: G.W. （㎏） | R1: 入数 | S1: 商品 形態 | T1: 備考
A2: 286938 | C2: PLUME CHAIR body | D2: プリュームチェア | E2: White | F2: 36000 | G2: =F2*1.1 -> 39600 | H2: =F2*0.7 -> 25200 | I2: W690 D690 H1030～1120 SH460～550 | J2: フレーム：PA66+GF(ナイロン) 座裏：ポリプロピレン ファブリック(座：ポリエステル) キャスター：ナイロンキャスター | K2: 中国 | L2: 13.8 | M2: 787 | N2: 323 | O2: 628 | P2: 16.5 | R2: 1 | S2: お客様組立品 | T2: 【機能】①座の上下調節、②ロッキングの強弱、③ロッキング固定/解除(1段階)/角度：最大130°、④アームの前後左右調節、⑤アームの上下調節(3段階)
A3: 286945 | C3: PLUME CHAIR option arm | E3: White | F3: 7000 | G3: =F3*1.1 -> 7700 | H3: =F3*0.7 -> 4900 | I3: ※取付時 W680 AH645～735 | J3: 張地：ポリエステル | K3: 中国 | L3: 11 | M3: 590.55 | N3: 457.2 | O3: 279.4 | P3: 12 | R3: 6 | S3: お客様組立品 | T3: 前後40mm、左右50mm、上下70mm幅
A4: 286952 | C4: PLUME CHAIR body | D4: プリュームチェア | E4: Black | F4: 36000 | G4: =F4*1.1 -> 39600 | H4: =F4*0.7 -> 25200 | I4: W690 D690 H1030～1120 SH460～550 | J4: フレーム：PA66+GF(ナイロン) 座裏：ポリプロピレン ファブリック(座：ポリエステル) キャスター：ナイロンキャスター | K4: 中国 | L4: 13.8 | M4: 787 | N4: 323 | O4: 628 | P4: 16.5 | R4: 1 | S4: お客様組立品 | T4: 【機能】①座の上下調節、②ロッキングの強弱、③ロッキング固定/解除(1段階)/角度：最大130°、④アームの前後左右調節、⑤アームの上下調節(3段階)
A5: 286969 | C5: PLUME CHAIR option arm | E5: Black | F5: 7000 | G5: =F5*1.1 -> 7700 | H5: =F5*0.7 -> 4900 | I5: ※取付時 W680 AH645～735 | J5: 張地：ポリエステル | K5: 中国 | L5: 11 | M5: 590.55 | N5: 457.2 | O5: 279.4 | P5: 12 | R5: 6 | S5: お客様組立品 | T5: 前後40mm、左右50mm、上下70mm幅
A6: 287164 | C6: LILIE SWIVEL CHAIR | D6: リーリエ スイベルチェア | E6: Grey | F6: 88000 | G6: =F6*1.1 -> 96800 | H6: =F6*0.7 -> 61600 | I6: W720 D730 H810 SH430 | J6: 張地：ポリエステル ベース：スチール(粉体塗装) | K6: 中国 | L6: 14.9 | M6: 768 | N6: 737 | O6: 501 | P6: 17.15 | R6: 1 | S6: お客様組立品 | T6: 回転式
A7: 290188 | C7: MELTONE 1P SOFA | D7: メルトーン 1P ソファ | E7: Grey | F7: 110000 | G7: =F7*1.1 -> 121000 | H7: =F7*0.7 -> 77000 | I7: W870 D720 H750 SH410 | J7: 張地：ポリエステル ベース：スチール(粉体塗装) | K7: 中国 | L7: 24.1 | M7: 889 | N7: 743 | O7: 781 | P7: 29.5 | R7: 1 | S7: お客様組立品
A8: 290195 | C8: MELTONE 2P SOFA | D8: メルトーン 2P ソファ | E8: Grey | F8: 172000 | G8: =F8*1.1 -> 189200 | H8: =F8*0.7 -> 120400 | I8: W1500 D720 H750 SH410 | J8: 張地：ポリエステル ベース：スチール(粉体塗装) | K8: 中国 | L8: 36.6 | M8: 1543 | N8: 743 | O8: 781 | P8: 43.6 | R8: 1 | S8: お客様組立品
A9: 290201 | C9: MELTONE 3P SOFA | D9: メルトーン 3P ソファ | E9: Grey | F9: 220000 | G9: =F9*1.1 -> 242000 | H9: =F9*0.7 -> 154000 | I9: W2160 D720 H750 SH410 | J9: 張地：ポリエステル ベース：スチール(粉体塗装) | K9: 中国 | L9: 48.5 | M9: 2178 | N9: 743 | O9: 781 | P9: 57.5 | R9: 1 | S9: お客様組立品
A10: 287201 | C10: PENTE 1P SOFA | D10: ペンテ 1P ソファ | E10: Grey | F10: 120000 | G10: =F10*1.1 -> 132000 | H10: =F10*0.7 -> 84000 | I10: W760 D760 H670 SH425 | J10: 張地：ポリエステル ベース：スチール(粉体塗装) | K10: 中国 | L10: 21.7 | M10: 762 | N10: 730 | O10: 502 | P10: 25.3 | R10: 1 | S10: お客様組立品
A11: 287218 | C11: PENTE 2P SOFA | D11: ペンテ 2P ソファ | E11: Grey | F11: 190000 | G11: =F11*1.1 -> 209000 | H11: =F11*0.7 -> 133000 | I11: W1425 D760 H670 SH425 | J11: 張地：ポリエステル ベース：スチール(粉体塗装) | K11: 中国 | L11: 36 | M11: 1499 | N11: 781 | O11: 502 | P11: 42 | R11: 1 | S11: お客様組立品
A12: 501772 | C12: HOAKA CHAIR | D12: ホアカ チェア | E12: Ivy green | F12: 26000 | G12: =F12*1.1 -> 28600 | H12: =F12*0.7 -> 18200 | I12: W545 D530 H780 SH485 AH690 | J12: 張地：ポリエステル ベース：スチール(粉体塗装) | K12: 中国 | L12: 6.55 | M12: 615 | N12: 560 | O12: 815 | P12: 16.5 | R12: 2 | S12: お客様組立品 | T12: スタッキング4脚可能
A13: 501758 | C13: HOAKA CHAIR | D13: ホアカ チェア | E13: Sand beige | F13: 26000 | G13: =F13*1.1 -> 28600 | H13: =F13*0.7 -> 18200 | I13: W545 D530 H780 SH485 AH690 | J13: 張地：ポリエステル ベース：スチール(粉体塗装) | K13: 中国 | L13: 6.55 | M13: 615 | N13: 560 | O13: 815 | P13: 16.5 | R13: 2 | S13: お客様組立品 | T13: スタッキング4脚可能
A14: 501765 | C14: HOAKA CHAIR | D14: ホアカ チェア | E14: Light grey | F14: 26000 | G14: =F14*1.1 -> 28600 | H14: =F14*0.7 -> 18200 | I14: W545 D530 H780 SH485 AH690 | J14: 張地：ポリエステル ベース：スチール(粉体塗装) | K14: 中国 | L14: 6 | M14: 620 | N14: 570 | O14: 830 | P14: 16.5 | R14: 2 | S14: お客様組立品 | T14: スタッキング4脚可能
A15: 501307 | C15: KANOA CASTER CHAIR | D15: カノア キャスターチェア | E15: Light grey | F15: 24000 | G15: =F15*1.1 -> 26400 | H15: =F15*0.7 -> 16800 | I15: W480 D545 H790 SH470 | J15: 張地：ポリエステル ベース：スチール(粉体塗装) キャスター：ポリプロピレンキャスター | K15: 中国 | L15: 5.95 | M15: 570 | N15: 470 | O15: 460 | P15: 13.7 | R15: 2 | S15: お客様組立品
A16: 501789 | C16: KANOA CASTER CHAIR | D16: カノア キャスターチェア | E16: Dark grey | F16: 24000 | G16: =F16*1.1 -> 26400 | H16: =F16*0.7 -> 16800 | I16: W480 D545 H790 SH470 | J16: 張地：ポリエステル ベース：スチール(粉体塗装) キャスター：ポリプロピレンキャスター | K16: 中国 | L16: 5.95 | M16: 570 | N16: 470 | O16: 460 | P16: 13.7 | R16: 2 | S16: お客様組立品
A17: 501130 | C17: LEHUA CHAIR | D17: レフアチェア | E17: Ginger | F17: 26000 | G17: =F17*1.1 -> 28600 | H17: =F17*0.7 -> 18200 | I17: W590 D570 H785 SH465 AH650 | J17: 張地：ポリプロピレン 脚部：ビーチ材 | K17: 中国 | L17: 5.73 | M17: 610 | N17: 600 | O17: 620 | P17: 15.45 | R17: 2 | S17: お客様組立品
A18: 501123 | C18: LEHUA CHAIR | D18: レフアチェア | E18: Brown | F18: 26000 | G18: =F18*1.1 -> 28600 | H18: =F18*0.7 -> 18200 | I18: W590 D570 H785 SH465 AH650 | J18: 張地：ポリプロピレン 脚部：ビーチ材 | K18: 中国 | L18: 5.73 | M18: 610 | N18: 600 | O18: 620 | P18: 15.45 | R18: 2 | S18: お客様組立品
A19: 501093 | C19: LEHUA CHAIR | D19: レフアチェア | E19: Black | F19: 26000 | G19: =F19*1.1 -> 28600 | H19: =F19*0.7 -> 18200 | I19: W590 D570 H785 SH465 AH650 | J19: 張地：ポリプロピレン 脚部：ビーチ材 | K19: 中国 | L19: 5.73 | M19: 610 | N19: 600 | O19: 620 | P19: 15.45 | R19: 2 | S19: お客様組立品
A20: 294971 | C20: SPIRO CHAIR Black body | D20: スピロ チェア ブラック ボディ | E20: Black | F20: 56000 | G20: =F20*1.1 -> 61600 | H20: =F20*0.7 -> 39200 | I20: W690 D690 H990～1070 SH445～525 キャスター間：W690 D690 座：W480 D575 | J20: 背：PA66+GF(強化ナイロン) 座：モールドウレタン、ポリエステル+ポリエラストマー 脚部：PA66+GF(強化ナイロン） キャスター：ポリウレタンキャスター | K20: 中国 | L20: 15.4 | M20: 813 | N20: 660 | O20: 324 | P20: 18.2 | R20: 1 | S20: お客様組立品 | T20: 【機能】 ①座の上下調節、前後60mm調節 ②ランバーサポート上下50mm調節 ③ロッキングの強弱調節 ④ロッキング固定/解除(3段階)/角度：最大130°
A21: 294988 | C21: SPIRO CHAIR Black option arm | D21: スピロ チェア ブラック オプション アーム | E21: Black | F21: 8000 | G21: =F21*1.1 -> 8800 | H21: =F21*0.7 -> 5600 | I21: ※取付時アーム幅 W705 AH640～720 | J21: PA66+GF(強化ナイロン)、ポリウレタン | K21: 中国 | L21: 11 | M21: 558.8 | N21: 292.1 | O21: 292.1 | P21: 12 | R21: 6 | S21: お客様組立品 | T21: 前後40mm、左右50mm、上下70mm幅調節可能
A22: 294995 | C22: SPIRO CHAIR Black option headrest | D22: スピロ チェア ブラック オプション ヘッドレスト | E22: Black | F22: 5000 | G22: =F22*1.1 -> 5500 | H22: =F22*0.7 -> 3500 | I22: ※取付時 H1110～1190 | J22: PA66+GF(強化ナイロン）、ポリエステル+ポリエラストマー | K22: 中国 | L22: 6 | M22: 812.8 | N22: 406.4 | O22: 406.4 | P22: 7 | R22: 6 | S22: お客様組立品 | T22: 上下100mm幅調節可能
A23: 295008 | C23: SPIRO CHAIR White body | D23: スピロ チェア ホワイト ボディ | E23: WHITE | F23: 56000 | G23: =F23*1.1 -> 61600 | H23: =F23*0.7 -> 39200 | I23: W690 D690 H990～1070 SH445～525 キャスター間：W690 D690 座：W480 D575 | J23: 背：PA66+GF(強化ナイロン) 座：モールドウレタン、ポリエステル+ポリエラストマー 脚部：PA66+GF(強化ナイロン） キャスター：ポリウレタンキャスター | K23: 中国 | L23: 15.4 | M23: 813 | N23: 660 | O23: 324 | P23: 18.2 | R23: 1 | S23: お客様組立品 | T23: 【機能】 ①座の上下調節、前後60mm調節 ②ランバーサポート上下50mm調節 ③ロッキングの強弱調節 ④ロッキング固定/解除(3段階)/角度：最大130°
A24: 295015 | C24: SPIRO CHAIR White option arm | D24: スピロ チェア ホワイト オプション アーム | E24: WHITE | F24: 8000 | G24: =F24*1.1 -> 8800 | H24: =F24*0.7 -> 5600 | I24: ※取付時アーム幅 W705 AH640～720 | J24: PA66+GF(強化ナイロン)、ポリウレタン | K24: 中国 | L24: 11 | M24: 558.8 | N24: 292.1 | O24: 292.1 | P24: 12 | R24: 6 | S24: お客様組立品 | T24: 前後40mm、左右50mm、上下70mm幅調節可能
A25: 295022 | C25: SPIRO CHAIR White option headrest | D25: スピロ チェア ホワイト オプション ヘッドレスト | E25: WHITE | F25: 5000 | G25: =F25*1.1 -> 5500 | H25: =F25*0.7 -> 3500 | I25: ※取付時 H1110～1190 | J25: PA66+GF(強化ナイロン）、ポリエステル+ポリエラストマー | K25: 中国 | L25: 6 | M25: 812.8 | N25: 406.4 | O25: 406.4 | P25: 7 | R25: 6 | S25: お客様組立品 | T25: 上下100mm幅調節可能
A26: 287072 | C26: VIVY CHAIR White body | D26: ヴィヴィー チェア ホワイト ボディ | F26: 56000 | G26: =F26*1.1 -> 61600 | H26: =F26*0.7 -> 39200 | I26: W690 D690 H985～1055 SH435～505 キャスター間：W690 D690 座：W480 D580 | J26: 背：PA66+GF(強化ナイロン) 座：モールドウレタン、ポリエステル+ポリエラストマー 脚部：PA66+GF(強化ナイロン） キャスター：ポリウレタンキャスター | K26: 中国 | L26: 17.7 | M26: 863 | N26: 323 | O26: 660 | P26: 20.4 | R26: 1 | S26: お客様組立品 | T26: 【機能】 ①座の上下調節、前後40mm調節 ②ランバーサポート上下50mm調節 ③ロッキングの強弱調節 ④ロッキング固定/解除(4段階)/角度：最大130°
A27: 287096 | C27: VIVY CHAIR White option arm | D27: ヴィヴィー チェア ホワイト オプション アーム | F27: 8000 | G27: =F27*1.1 -> 8800 | H27: =F27*0.7 -> 5600 | I27: 取付時アーム幅 W710 AH645～715 | J27: PA66+GF(強化ナイロン)、ポリウレタン | K27: 中国 | L27: 11 | M27: 558.8 | N27: 292.1 | O27: 292.1 | P27: 12 | R27: 6 | S27: お客様組立品 | T27: 前後40mm、左右50mm、上下70mm幅調節可能
A28: 287089 | C28: VIVY CHAIR White option headrest | D28: ヴィヴィー チェア ホワイト オプション ヘッドレスト | F28: 5000 | G28: =F28*1.1 -> 5500 | H28: =F28*0.7 -> 3500 | I28: 取付時 H1100～1170 | J28: PA66+GF(強化ナイロン）、ポリエステル+ポリエラストマー | K28: 中国 | L28: 9 | M28: 812.8 | N28: 406.4 | O28: 406.4 | P28: 10 | R28: 8 | S28: お客様組立品 | T28: 上下100mm幅調節可能
A29: 286679 | C29: VIVY CHAIR Black body | D29: ヴィヴィー チェア ブラック ボディ | F29: 56000 | G29: =F29*1.1 -> 61600 | H29: =F29*0.7 -> 39200 | I29: W690 D690 H985～1055 SH435～505 キャスター間：W690 D690 座：W480 D580 | J29: 背：PA66+GF(強化ナイロン) 座：モールドウレタン、ポリエステル+ポリエラストマー 脚部：PA66+GF(強化ナイロン） キャスター：ポリウレタンキャスター | K29: 中国 | L29: 17.7 | M29: 863 | N29: 323 | O29: 660 | P29: 20.4 | R29: 1 | S29: お客様組立品 | T29: 【機能】 ①座の上下調節、前後40mm調節 ②ランバーサポート上下50mm調節 ③ロッキングの強弱調節 ④ロッキング固定/解除(4段階)/角度：最大130°
A30: 286891 | C30: VIVY CHAIR Black option arm | D30: ヴィヴィー チェア ブラック オプション アーム | F30: 8000 | G30: =F30*1.1 -> 8800 | H30: =F30*0.7 -> 5600 | I30: 取付時アーム幅 W710 AH645～715 | J30: PA66+GF(強化ナイロン)、ポリウレタン | K30: 中国 | L30: 11 | M30: 558.8 | N30: 292.1 | O30: 292.1 | P30: 12 | R30: 6 | S30: お客様組立品 | T30: 前後40mm、左右50mm、上下70mm幅調節可能
A31: 286884 | C31: VIVY CHAIR Black option headrest | D31: ヴィヴィー チェア ブラック オプション ヘッドレスト | F31: 5000 | G31: =F31*1.1 -> 5500 | H31: =F31*0.7 -> 3500 | I31: 取付時 H1100～1170 | J31: PA66+GF(強化ナイロン）、ポリエステル+ポリエラストマー | K31: 中国 | L31: 9 | M31: 812.8 | N31: 406.4 | O31: 406.4 | P31: 10 | R31: 8 | S31: お客様組立品 | T31: 上下100mm幅調節可能
A32: 294926 | C32: ARISTA CASTER CHAIR Ivory | D32: アリスタ キャスター チェア アイボリー | F32: 39000 | G32: =F32*1.1 -> 42900 | H32: =F32*0.7 -> 27300 | I32: W620 D620 H770～860 SH420～510 AH645～735 キャスター間：W620 D620 座 アーム幅：W565 D550 座 シート幅：W475 D430 | J32: 背：PA66+GF(強化ナイロン) 座：モールドウレタン、ポリエステル+ポリエラストマー 脚部：PA66+GF(強化ナイロン） キャスター：ポリウレタンキャスター | K32: 中国 | L32: 9.7 | M32: 616 | N32: 572 | O32: 559 | P32: 11.65 | R32: 1 | S32: お客様組立品 | T32: 【機能】 ①座の上下調節 ②背座一体ロッキング（背チルト）/最大角度115°
A33: 294919 | C33: ARISTA CASTER CHAIR Sesame grey | D33: アリスタ キャスター チェア セサミグレー | F33: 39000 | G33: =F33*1.1 -> 42900 | H33: =F33*0.7 -> 27300 | I33: W620 D620 H770～860 SH420～510 AH645～735 キャスター間：W620 D620 座 アーム幅：W565 D550 座 シート幅：W475 D430 | J33: 背：PA66+GF(強化ナイロン) 座：モールドウレタン、ポリエステル+ポリエラストマー 脚部：PA66+GF(強化ナイロン） キャスター：ポリウレタンキャスター | K33: 中国 | L33: 9.7 | M33: 616 | N33: 572 | O33: 559 | P33: 11.65 | R33: 1 | S33: お客様組立品 | T33: 【機能】 ①座の上下調節 ②背座一体ロッキング（背チルト）/最大角度115°
A34: 294933 | C34: ARISTA CASTER CHAIR Chill red | D34: アリスタ キャスター チェア チリレッド | F34: 39000 | G34: =F34*1.1 -> 42900 | H34: =F34*0.7 -> 27300 | I34: W620 D620 H770～860 SH420～510 AH645～735 キャスター間：W620 D620 座 アーム幅：W565 D550 座 シート幅：W475 D430 | J34: 背：PA66+GF(強化ナイロン) 座：モールドウレタン、ポリエステル+ポリエラストマー 脚部：PA66+GF(強化ナイロン） キャスター：ポリウレタンキャスター | K34: 中国 | L34: 9.7 | M34: 616 | N34: 572 | O34: 559 | P34: 11.65 | R34: 1 | S34: お客様組立品 | T34: 【機能】 ①座の上下調節 ②背座一体ロッキング（背チルト）/最大角度115°
A35: 294957 | C35: ARISTA MEETING CHAIR Ivory | D35: アリスタ ミーティング チェア アイボリー | F35: 36000 | G35: =F35*1.1 -> 39600 | H35: =F35*0.7 -> 25200 | I35: W565 D545 H800 SH450 AH650 | J35: 背：PA66+GF(強化ナイロン) 座：モールドウレタン、ポリエステル+ポリエラストマー 脚部：PA66+GF(強化ナイロン） キャスター：ポリウレタンキャスター | K35: 中国 | L35: 12.7 | M35: 603 | N35: 845 | O35: 578 | P35: 16.3 | R35: 1 | S35: お客様組立品 | T35: 平行スタッキング可能
A36: 294940 | C36: ARISTA MEETING CHAIR Sesame grey | D36: アリスタ ミーティング チェア セサミグレー | F36: 36000 | G36: =F36*1.1 -> 39600 | H36: =F36*0.7 -> 25200 | I36: W565 D545 H800 SH450 AH650 | J36: 背：PA66+GF(強化ナイロン) 座：モールドウレタン、ポリエステル+ポリエラストマー 脚部：PA66+GF(強化ナイロン） キャスター：ポリウレタンキャスター | K36: 中国 | L36: 12.7 | M36: 603 | N36: 845 | O36: 578 | P36: 16.3 | R36: 1 | S36: お客様組立品 | T36: 平行スタッキング可能
A37: 294964 | C37: ARISTA MEETING CHAIR Basil Green | D37: アリスタ ミーティング チェア バジルグリーン | F37: 36000 | G37: =F37*1.1 -> 39600 | H37: =F37*0.7 -> 25200 | I37: W565 D545 H800 SH450 AH650 | J37: 背：PA66+GF(強化ナイロン) 座：モールドウレタン、ポリエステル+ポリエラストマー 脚部：PA66+GF(強化ナイロン） キャスター：ポリウレタンキャスター | K37: 中国 | L37: 12.7 | M37: 603 | N37: 845 | O37: 578 | P37: 16.3 | R37: 1 | S37: お客様組立品 | T37: 平行スタッキング可能
A38: 295039 | C38: NEW OCUS CHAIR Black | D38: ニュー オーカス チェア ブラック | F38: 48000 | G38: =F38*1.1 -> 52800 | H38: =F38*0.7 -> 33600 | I38: W680 D680 H800～860 SH440～500 キャスター間：W680 D680 座：W470 D552 | J38: 背：PA66+GF(強化ナイロン) 座：モールドウレタン、ポリエステル+ポリエラストマー 脚部：PA66+GF(強化ナイロン） キャスター：ポリウレタンキャスター | K38: 中国 | L38: 11.2 | M38: 855 | N38: 670 | O38: 340 | P38: 13.7 | R38: 1 | S38: お客様組立品 | T38: 【機能】 ①座の上下調節 ②背座一体ロッキング（背チルト）/最大角度130°
A39: 295046 | C39: NEW OCUS CHAIR White | D39: ニュー オーカス チェア ホワイト | F39: 48000 | G39: =F39*1.1 -> 52800 | H39: =F39*0.7 -> 33600 | I39: W680 D680 H800～860 SH440～500 キャスター間：W680 D680 座：W470 D552 | J39: 背：PA66+GF(強化ナイロン) 座：モールドウレタン、ポリエステル+ポリエラストマー 脚部：PA66+GF(強化ナイロン） キャスター：ポリウレタンキャスター | K39: 中国 | L39: 11.2 | M39: 855 | N39: 670 | O39: 340 | P39: 13.7 | R39: 1 | S39: お客様組立品 | T39: 【機能】 ①座の上下調節 ②背座一体ロッキング（背チルト）/最大角度130°
A40: 287140 | C40: NOG CASTER CHAIR Amber | D40: ノグ キャスター チェア アンバー | F40: 59000 | G40: =F40*1.1 -> 64900 | H40: =F40*0.7 -> 41300 | I40: W650 D650 H800～865 SH450～515 AH730～795 キャスター間：W650 D650 座 アーム幅：W600 D585 座 シート幅：W485 D440 | J40: 背、座：モールドウレタン+PU 脚部：アルミニウム キャスター：ポリウレタンキャスター | K40: 中国 | L40: 13.5 | M40: 629 | N40: 603 | O40: 559 | P40: 16.2 | R40: 1 | S40: お客様組立品 | T40: 【機能】 ①座の上下調節 ②背座一体ロッキング（背チルト）/最大角度120°
A41: 287157 | C41: NOG CASTER CHAIR Night Grey | D41: ノグ キャスター チェア ナイトグレー | F41: 59000 | G41: =F41*1.1 -> 64900 | H41: =F41*0.7 -> 41300 | I41: W650 D650 H800～865 SH450～515 AH730～795 キャスター間：W650 D650 座 アーム幅：W600 D585 座 シート幅：W485 D440 | J41: 背、座：モールドウレタン+PU 脚部：アルミニウム キャスター：ポリウレタンキャスター | K41: 中国 | L41: 13.5 | M41: 629 | N41: 603 | O41: 559 | P41: 16.2 | R41: 1 | S41: お客様組立品 | T41: 【機能】 ①座の上下調節 ②背座一体ロッキング（背チルト）/最大角度120°
A42: 294841 | C42: NOG CASTER CHAIR Ivory | D42: ノグ キャスター チェア アイボリー | F42: 59000 | G42: =F42*1.1 -> 64900 | H42: =F42*0.7 -> 41300 | I42: W650 D650 H800～865 SH450～515 AH730～795 キャスター間：W650 D650 座 アーム幅：W600 D585 座 シート幅：W485 D440 | J42: 背、座：モールドウレタン+ポリエステル 脚部：アルミニウム キャスター：ポリウレタンキャスター | K42: 中国 | L42: 13.5 | M42: 629 | N42: 603 | O42: 559 | P42: 16.2 | R42: 1 | S42: お客様組立品 | T42: 【機能】 ①座の上下調節 ②背座一体ロッキング（背チルト）/最大角度120°
A43: 294834 | C43: NOG CASTER CHAIR Sesame grey | D43: ノグ キャスター チェア セサミグレー | F43: 59000 | G43: =F43*1.1 -> 64900 | H43: =F43*0.7 -> 41300 | I43: W650 D650 H800～865 SH450～515 AH730～795 キャスター間：W650 D650 座 アーム幅：W600 D585 座 シート幅：W485 D440 | J43: 背、座：モールドウレタン+ポリエステル 脚部：アルミニウム キャスター：ポリウレタンキャスター | K43: 中国 | L43: 13.5 | M43: 629 | N43: 603 | O43: 559 | P43: 16.2 | R43: 1 | S43: お客様組立品 | T43: 【機能】 ①座の上下調節 ②背座一体ロッキング（背チルト）/最大角度120°
A44: 287102 | C44: ROTOM CHAIR Amber | D44: ロトムチェア アンバー | F44: 32000 | G44: =F44*1.1 -> 35200 | H44: =F44*0.7 -> 22400 | I44: W490 D520 H780 SH465 | J44: 背、座：モールドウレタン+PU 脚部：スチール | K44: 中国 | L44: 6 | M44: 527 | N44: 483 | O44: 813 | P44: 13.6 | R44: 1 | S44: FIX
A45: 287119 | C45: ROTOM CHAIR Night grey | D45: ロトムチェア ナイトグレー | F45: 32000 | G45: =F45*1.1 -> 35200 | H45: =F45*0.7 -> 22400 | I45: W490 D520 H780 SH465 | J45: 背、座：モールドウレタン+PU 脚部：スチール | K45: 中国 | L45: 6 | M45: 527 | N45: 483 | O45: 813 | P45: 13.6 | R45: 1 | S45: FIX
A46: 294803 | C46: ROTOM CHAIR Ivory | D46: ロトムチェア アイボリー | F46: 32000 | G46: =F46*1.1 -> 35200 | H46: =F46*0.7 -> 22400 | I46: W490 D520 H780 SH465 | J46: 背、座：モールドウレタン+PU 脚部：スチール | K46: 中国 | L46: 6 | M46: 527 | N46: 483 | O46: 813 | P46: 13.6 | R46: 1 | S46: FIX
A47: 294797 | C47: ROTOM CHAIR Sesame grey | D47: ロトムチェア セサミグレー | F47: 32000 | G47: =F47*1.1 -> 35200 | H47: =F47*0.7 -> 22400 | I47: W490 D520 H780 SH465 | J47: 背、座：モールドウレタン+PU 脚部：スチール | K47: 中国 | L47: 6 | M47: 527 | N47: 483 | O47: 813 | P47: 13.6 | R47: 1 | S47: FIX
A48: 294667 | C48: DIMPLE CHAIR Cinnamon | D48: ディンプル チェア シナモン | F48: 28000 | G48: =F48*1.1 -> 30800 | H48: =F48*0.7 -> 19600 | I48: W540 D560 H790 SH470 AH660 | J48: ファブリック、スチール | K48: 中国 | L48: 6.9 | M48: 540 | N48: 560 | O48: 790 | P48: 9.6 | R48: 1 | S48: FIX
A49: 294674 | C49: DIMPLE CHAIR Pepper grey | D49: ディンプル チェア ペッパーグレー | F49: 28000 | G49: =F49*1.1 -> 30800 | H49: =F49*0.7 -> 19600 | I49: W540 D560 H790 SH470 AH660 | J49: ファブリック、スチール | K49: 中国 | L49: 6.9 | M49: 540 | N49: 560 | O49: 790 | P49: 9.6 | R49: 1 | S49: FIX
A50: 294735 | C50: FLONE SIDE CHAIR Mustard | D50: フローネ サイド チェア マスタード | F50: 32000 | G50: =F50*1.1 -> 35200 | H50: =F50*0.7 -> 22400 | I50: W470 D560 H820 SH480 | J50: ファブリック、スチール | K50: 中国 | L50: 6.9 | M50: 470 | N50: 560 | O50: 820 | P50: 9.8 | R50: 1 | S50: FIX
A51: 294728 | C51: FLONE SIDE CHAIR Smoky grey | D51: フローネ サイド チェア スモーキーグレー | F51: 32000 | G51: =F51*1.1 -> 35200 | H51: =F51*0.7 -> 22400 | I51: W470 D560 H820 SH480 | J51: ファブリック、スチール | K51: 中国 | L51: 6.9 | M51: 470 | N51: 560 | O51: 820 | P51: 9.8 | R51: 1 | S51: FIX
A52: 294643 | C52: MOKUIS SIDE CHAIR | D52: モクイス サイド チェア | F52: 28000 | G52: =F52*1.1 -> 30800 | H52: =F52*0.7 -> 19600 | I52: W485 D505 H760 SH450 | J52: 合板、スチール | K52: 中国 | L52: 6.3 | M52: 485 | N52: 505 | O52: 760 | P52: 7.3 | R52: 1 | S52: FIX
A53: 294650 | C53: MOKUIS COUNTER CHAIR | D53: モクイス カウンター チェア | F53: 33000 | G53: =F53*1.1 -> 36300 | H53: =F53*0.7 -> 23100 | I53: W530 D530 H1060 SH760 | J53: 合板、スチール | K53: 中国 | L53: 8 | M53: 530 | N53: 530 | O53: 1060 | P53: 10 | R53: 1 | S53: FIX
A54: 293639 | C54: JIGGLY STOOL Grey×Light grey | D54: ジグリー スツール グレー×ライトグレー | F54: 29000 | G54: =F54*1.1 -> 31900 | H54: =F54*0.7 -> 20300 | I54: W332 D332 H546～790 | J54: 布: 100% polyester クッション材:ウレタンフォーム 脚部ベース:PA+GF / PP / TPR ガスシリンダーセット: スチール / POM ガスシリンダー外筒カバー: PP | K54: 台湾 | L54: 5.58 | M54: 413 | N54: 138 | O54: 690 | P54: 7.6 | R54: 1 | S54: お客様組立品
A55: 293646 | C55: JIGGLY STOOL Grey×Brown | D55: ジグリー スツール グレー×ブラウン | F55: 29000 | G55: =F55*1.1 -> 31900 | H55: =F55*0.7 -> 20300 | I55: W332 D332 H546～790 | J55: 布: 100% polyester クッション材:ウレタンフォーム 脚部ベース:PA+GF / PP / TPR ガスシリンダーセット: スチール / POM ガスシリンダー外筒カバー: PP | K55: 台湾 | L55: 5.58 | M55: 413 | N55: 138 | O55: 690 | P55: 7.6 | R55: 1 | S55: お客様組立品
... A60: 294742 | C60: FLONE LOUNGE CHAIR Smoky grey | D60: フローネ ラウンジ チェア スモーキーグレー | F60: 42000 | G60: =F60*1.1 -> 46200 | H60: =F60*0.7 -> 29400 | I60: W720 D725 H690 SH400 | J60: ファブリック、スチール | K60: 中国 | L60: 11.3 | M60: 720 | N60: 725 | O60: 690 | P60: 14.85 | R60: 1 | S60: FIX
A61: 293738 | C61: conpas desk (natural) | D61: コンパス デスク ナチュラル | F61: 29000 | G61: =F61*1.1 -> 31900 | H61: =F61*0.7 -> 20300 | I61: W1200 D600 H720 | J61: メラミン、スチール | K61: 台湾 | L61: 17.63 | M61: 1213 | N61: 623 | O61: 188 | P61: 20 | R61: 1 | S61: お客様組立品
A62: 293752 | C62: conpas desk (charcoal) | D62: コンパス デスク チャコール | F62: 29000 | G62: =F62*1.1 -> 31900 | H62: =F62*0.7 -> 20300 | I62: W1200 D600 H720 | J62: メラミン、スチール | K62: 台湾 | L62: 17.63 | M62: 1213 | N62: 623 | O62: 188 | P62: 20 | R62: 1 | S62: お客様組立品
A63: 293745 | C63: conpas desk (beige) | D63: コンパス デスク ベージュ | F63: 29000 | G63: =F63*1.1 -> 31900 | H63: =F63*0.7 -> 20300 | I63: W1200 D600 H720 | J63: メラミン、スチール | K63: 台湾 | L63: 17.63 | M63: 1213 | N63: 623 | O63: 188 | P63: 20 | R63: 1 | S63: お客様組立品
A64: 293660 | C64: HOUGAN DESK TOP Charcoal | D64: ニュー ホウガン デスク トップ チャコール | F64: 40000 | G64: =F64*1.1 -> 44000 | H64: =F64*0.7 -> 28000 | I64: W1200 D600 t25 | J64: 天板：パーティクルボード メラミン化粧板 配線トレー：スチール 粉体塗装 | K64: 台湾 | L64: 25.03 | M64: 1324 | N64: 1266 | O64: 103 | P64: 30 | R64: 1 | S64: お客様組立品
A65: 293677 | C65: HOUGAN DESK END LEG Black(4pcs/1set) | D65: ニュー ホウガン デスク エンド レッグ スチール | F65: 20000 | G65: =F65*1.1 -> 22000 | H65: =F65*0.7 -> 14000 | I65: W380 D180 H695 | J65: 脚部：スチール 粉体塗装 配線カバー：スチール 粉体塗装 | K65: 台湾 | L65: 11.64 | M65: 780 | N65: 388 | O65: 188 | P65: 13.28 | R65: 1 | S65: お客様組立品 | T65: 4pcs/1set
A66: 293684 | C66: HOUGAN DESK CENTER LEG Black(2pcs/1set) | D66: ニュー ホウガン デスク センター レッグ スチール | F66: 22000 | G66: =F66*1.1 -> 24200 | H66: =F66*0.7 -> 15400 | I66: W380 D180 H695 | J66: 脚部：スチール 粉体塗装 配線カバー：スチール 粉体塗装 | K66: 台湾 | L66: 7.05 | M66: 780 | N66: 388 | O66: 188 | P66: 8.61 | R66: 1 | S66: お客様組立品 | T66: 2pcs/1set
A67: 293653 | C67: HOUGAN DESK TOP Natural | D67: ニュー ホウガン デスク トップ ナチュラル | F67: 40000 | G67: =F67*1.1 -> 44000 | H67: =F67*0.7 -> 28000 | I67: W1200 D600 t25 | J67: 天板：パーティクルボード メラミン化粧板 配線トレー：スチール 粉体塗装 | K67: 台湾 | L67: 25.03 | M67: 1324 | N67: 1266 | O67: 103 | P67: 30 | R67: 1 | S67: お客様組立品
A68: 293691 | C68: HOUGAN DESK END LEG Wood(4pcs/1set) | D68: ニュー ホウガン デスク エンド レッグ ウッド | F68: 47500 | G68: =F68*1.1 -> 52250 | H68: =F68*0.7 -> 33250 | I68: W380 D180 H695 | J68: 脚部：OAK NC塗装 スチール 粉体塗装 | K68: 台湾 | L68: 11.64 | M68: 780 | N68: 388 | O68: 188 | P68: 13.28 | R68: 1 | S68: お客様組立品 | T68: 4pcs/1set
A69: 293707 | C69: HOUGAN DESK CENTER LEG Wood(2pcs/1set) | D69: ニュー ホウガン デスク センター レッグ ウッド | F69: 36000 | G69: =F69*1.1 -> 39600 | H69: =F69*0.7 -> 25200 | I69: W380 D180 H695 | J69: 脚部：OAK NC塗装 スチール 粉体塗装 | K69: 台湾 | L69: 7.05 | M69: 780 | N69: 388 | O69: 188 | P69: 8.61 | R69: 1 | S69: お客様組立品 | T69: 2pcs/1set
A70: 294209 | C70: (SET2)BASED-WIZ PERSONAL BOOTH Graphite | D70: ベースドウィズ パーソナルブース グラファイト | F70: 150000 | G70: =F70*1.1 -> 165000 | H70: =F70*0.7 -> 105000 | I70: W1085 D870 H1415 SH440 TH730 | J70: ファブリック、スチール、メラミン | K70: 中国 | L70: 27.9 | M70: 1430 | N70: 1050 | O70: 210 | P70: 31.2 | R70: 1 | S70: お客様組立品
L71: 10 | M71: 600 | N71: 620 | O71: 830 | P71: 12.5 | R71: 1
A72: 294216 | C72: (SET2)BASED-WIZ PERSONAL BOOTH Cream | D72: ベースドウィズ パーソナルブース クリーム | F72: 150000 | G72: =F72*1.1 -> 165000 | H72: =F72*0.7 -> 105000 | I72: W1085 D870 H1415 SH440 TH730 | J72: ファブリック、スチール、メラミン | K72: 中国 | L72: 27.9 | M72: 1430 | N72: 1050 | O72: 210 | P72: 31.2 | R72: 1 | S72: お客様組立品
L73: 10 | M73: 600 | N73: 620 | O73: 830 | P73: 12.5 | R73: 1
A74: 294223 | C74: BASED-WIZ PERSONAL DESK Graphite | D74: ベースドウィズ パーソナルデスク グラファイト | F74: 95000 | G74: =F74*1.1 -> 104500 | H74: =F74*0.7 -> 66500 | I74: W1020 D720 H1415 TH730 | J74: ファブリック、スチール、メラミン | K74: 中国 | L74: 22.3 | M74: 1440 | N74: 990 | O74: 220 | P74: 24.8 | R74: 1 | S74: お客様組立品
A75: 294230 | C75: BASED-WIZ PERSONAL DESK Cream | D75: ベースドウィズ パーソナルデスク クリーム | F75: 95000 | G75: =F75*1.1 -> 104500 | H75: =F75*0.7 -> 66500 | I75: W1020 D720 H1415 TH730 | J75: ファブリック、スチール、メラミン | K75: 中国 | L75: 22.3 | M75: 1440 | N75: 990 | O75: 220 | P75: 24.8 | R75: 1 | S75: お客様組立品
A76: 293790 | C76: JUNGLE-GYM LOW CABINET | D76: ジャングルジムシェルフ ロー キャビネット | F76: 75000 | G76: =F76*1.1 -> 82500 | H76: =F76*0.7 -> 52500 | I76: W800 D400 H1220 | J76: メラミン、ウッド | K76: 台湾 | L76: 46.73 | M76: 862 | N76: 462 | O76: 1285 | P76: 53 | R76: 1 | S76: お客様組立品
A77: 293806 | C77: JUNGLE-GYM HIGH CABINET | D77: ジャングルジムシェルフ ハイ キャビネット | F77: 125000 | G77: =F77*1.1 -> 137500 | H77: =F77*0.7 -> 87500 | I77: W800 D400 H2020 | J77: メラミン、ウッド | K77: 台湾 | L77: 29.54 | M77: 862 | N77: 462 | O77: 855 | P77: 33 | R77: 1 | S77: お客様組立品
K78: 台湾 | L78: 46.73 | M78: 862 | N78: 462 | O78: 1285 | P78: 53
C79: JUNGLE-GYM SHELF SET 5X3 | D79: ジャングルジムシェルフ セット 5X3 | F79: 131000 | G79: =F79*1.1 -> 144100 | H79: =F79*0.7 -> 91700 | I79: W1200 D400 H2025 | J79: スチール、メラミン | K79: 台湾 | S79: お客様組立品 | T79: 275192 ジャングルジムシェルフ 5ティア X 1PCS 275208 ジャングルジムシェルフ 5アドオンX 2PCS 293769 ジャングルジムシェルフボード X 18PCS(9セット)
D80: ジャングルジムシェルフ5ティア | K80: 台湾 | L80: 8.74 | M80: 455 | N80: 2100 | O80: 95 | P80: 12.22 | Q80: x1
D81: ジャングルジムシェルフ5アドオン | K81: 台湾 | L81: 5.92 | M81: 425 | N81: 2080 | O81: 140 | P81: 9.78 | Q81: x2
D82: ジャングルジムシェルフシェルフボード(2pcs/1セット) | K82: 台湾 | L82: 3.02 | M82: 431 | N82: 394 | O82: 52 | P82: 3.6 | Q82: x9セット
C83: JUNGLE-GYM SHELF SET 3X3 | D83: ジャングルジムシェルフ セット 3X3 | F83: 99000 | G83: =F83*1.1 -> 108900 | H83: =F83*0.7 -> 69300 | I83: W1200 D 400 H1235 | J83: スチール、メラミン | K83: 台湾 | S83: お客様組立品 | T83: 275215 ジャングルジムシェルフ 3ティア X 1PCS 275222 ジャングルジムシェルフ 3アドオンX 2PCS 293769 ジャングルジムシェルフボード X 12PCS(6セット)
D84: ジャングルジムシェルフ3ティア | L84: 5.64 | M84: 1300 | N84: 455 | O84: 100 | P84: 7.64 | Q84: x1
D85: ジャングルジムシェルフ3アドオン | L85: 3.76 | M85: 1270 | N85: 430 | O85: 140 | P85: 6.22 | Q85: x2
D86: ジャングルジムシェルフシェルフボード(2pcs/1セット) | L86: 3.02 | M86: 431 | N86: 394 | O86: 52 | P86: 3.6 | Q86: x6セット
A87: 293585 | C87: RANGO WHITE BOARD | D87: ランゴ ホワイト ボード | F87: 80000 | G87: =F87*1.1 -> 88000 | H87: =F87*0.7 -> 56000 | I87: W900 D500 H1800 | J87: フレーム：アルミ 粉体塗装 脚部：アルミダイキャスト 粉体塗装 ペントレー：スチール 粉体塗装 ホワイトボード：鋼板、ハニカムボード | K87: 台湾 | L87: 18.45 | M87: 1946 | N87: 932 | O87: 81 | P87: 23.19 | R87: 1 | S87: お客様組立品
A88: 293592 | C88: RANGO STEEL SHELF | D88: ランゴ スチール シェルフ | F88: 95000 | G88: =F88*1.1 -> 104500 | H88: =F88*0.7 -> 66500 | I88: W900 D500 H1800 | J88: フレーム：アルミ 粉体塗装 脚部：アルミダイキャスト 粉体塗装 シェルフ：スチール 粉体塗装 | K88: 台湾 | L88: 16.31 | M88: 1838 | N88: 932 | O88: 81 | P88: 20.85 | R88: 1 | S88: お客様組立品
A89: 293608 | C89: RANGO TV STAND | D89: ランゴ TV スタンド | F89: 105000 | G89: =F89*1.1 -> 115500 | H89: =F89*0.7 -> 73500 | I89: W1200 D500 H1800 | J89: フレーム：アルミ 粉体塗装 脚部：アルミダイキャスト 粉体塗装 ディスプレイ取付部：スチール 粉体塗装 棚板：スチール 粉体塗装 | K89: 台湾 | L89: 27.91 | M89: 1838 | N89: 1232 | O89: 81 | P89: 34.28 | R89: 1 | S89: お客様組立品
A90: 284101 | C90: (SET4)FLEX WIZ CABINET W1200 5 TIER | D90: フレックスウィズキャビネット5ティア | F90: 233000 | G90: =F90*1.1 -> 256300 | H90: =F90*0.7 -> 163100 | I90: W1200 D400 H1940 | J90: スチール、オークウッド 4個口 | L90: 75 | S90: お客様組立品 | T90: 可動棚・配線孔・アジャスター付き
M91: 1320 | N91: 450 | O91: 205
M92: 1930 | N92: 445 | O92: 65
M93: 1910 | N93: 670 | O93: 60
M94: 1900 | N94: 690 | O94: 60
A95: 284118 | C95: (SET2)FLEX WIZ CABINET W1200 3 TIER | D95: フレックスウィズキャビネット3ティア | F95: 187000 | G95: =F95*1.1 -> 205700 | H95: =F95*0.7 -> 130900 | I95: W1200 D400 H1180 | J95: スチール、オークウッド 2個口 | L95: 50 | S95: お客様組立品 | T95: 可動棚・配線孔・アジャスター付き
M96: 1310 | N96: 450 | O96: 140
M97: 1190 | N97: 640 | O97: 170
A98: 293820 | C98: NOMUSS TRUSH BOX Charcoal | D98: NOMUSS TRUSH BOX Charcoal | F98: 94000 | G98: =F98*1.1 -> 103400 | H98: =F98*0.7 -> 65800 | I98: W1000 D500 H1000 | J98: メラミン、スチール | L98: 43.85 | M98: 1062 | N98: 562 | O98: 1065 | P98: 50.9 | R98: 1 | T98: 推奨ゴミ箱サイズ：45L 内ゴミ箱は付属しておりません
A99: 293820_OPTION | C99: オプション | D99: ゴミ箱45Lサイズ 3個 別売り 1pcs @4300 x 3 | H99: 12900
A100: 293813 | C100: NOMUSS TRUSH BOX Beige | D100: NOMUSS TRUSH BOX Beige | F100: 94000 | G100: =F100*1.1 -> 103400 | H100: =F100*0.7 -> 65800 | I100: W1000 D500 H1000 | J100: メラミン、スチール | L100: 43.85 | M100: 1062 | N100: 562 | O100: 1065 | P100: 50.9 | R100: 1 | T100: 推奨ゴミ箱サイズ：45L 内ゴミ箱は付属しておりません
C101: オプション | D101: ゴミ箱45Lサイズ 3個 別売り 1pcs @4300 x 3 | H101: 12900
A102: 293844 | C102: NOMUSS CABINET Charcoal | D102: ノーマス キャビネット チャコール | F102: 97000 | G102: =F102*1.1 -> 106700 | H102: =F102*0.7 -> 67900 | I102: W1000 D500 H1000 | J102: メラミン | L102: 58.3 | M102: 1062 | N102: 562 | O102: 1065 | P102: 65.3 | R102: 1 | T102: 可動棚・配線孔付き
A103: 293837 | C103: NOMUSS CABINET Beige | D103: ノーマス キャビネット ベージュ | F103: 97000 | G103: =F103*1.1 -> 106700 | H103: =F103*0.7 -> 67900 | I103: W1000 D500 H1000 | J103: メラミン | L103: 58.3 | M103: 1062 | N103: 562 | O103: 1065 | P103: 65.3 | R103: 1 | T103: 可動棚・配線孔付き
C104: FLEX-WIZ STORAGE OPEN 1180 SET BODY: White LEG: Steel Black | D104: フレックスウィズオープン1180セット 本体：ホワイト 脚：スチール ブラック | F104: 80000 | G104: =F104*1.1 -> 88000 | H104: =F104*0.7 -> 56000 | I104: W1177 D400 H1250 | J104: スチール | S104: お客様組立品 | T104: 可動棚付き
...

Sheet 送料対応表
A1: 都道府県 | B1: 送料 | C1: お届け日数
A2: 北海道 | B2: 別途見積もり | C2: 要相談
A3: 青森県 | B3: 0 | C3: 2日～3日
A4: 岩手県 | B4: 0 | C4: 1日～2日
A5: 宮城県 | B5: 0 | C5: 1日～2日
A6: 秋田県 | B6: 0 | C6: 1日～2日
A7: 山形県 | B7: 0 | C7: 1日～2日
A8: 福島県 | B8: 0 | C8: 1日～2日
A9: 茨城県 | B9: 0 | C9: 1日～2日
A10: 栃木県 | B10: 0 | C10: 1日～2日
A11: 群馬県 | B11: 0 | C11: 1日～2日
A12: 埼玉県 | B12: 0 | C12: 1日～2日
A13: 千葉県 | B13: 0 | C13: 1日～2日
A14: 東京都 | B14: 0 | C14: 1日～2日
... A36: 山口県 | B36: 0 | C36: 2日～3日
A37: 徳島県 | B37: 別途見積もり | C37: 要相談
A38: 香川県 | B38: 別途見積もり | C38: 要相談
A39: 愛媛県 | B39: 別途見積もり | C39: 要相談
A40: 高知県 | B40: 別途見積もり | C40: 要相談
A41: 福岡県 | B41: 別途見積もり | C41: 要相談
A42: 佐賀県 | B42: 別途見積もり | C42: 要相談
A43: 長崎県 | B43: 別途見積もり | C43: 要相談
A44: 熊本県 | B44: 別途見積もり | C44: 要相談
A45: 大分県 | B45: 別途見積もり | C45: 要相談
A46: 宮崎県 | B46: 別途見積もり | C46: 要相談
A47: 鹿児島県 | B47: 別途見積もり | C47: 要相談
A48: 沖縄県 | B48: 別途見積もり | C48: 要相談
